wsgigzip/__init__.py
wsgigzip/gzip.py
wsgigzip-0.1.4.dist-info/DESCRIPTION.rst
wsgigzip-0.1.4.dist-info/METADATA
wsgigzip-0.1.4.dist-info/RECORD
wsgigzip-0.1.4.dist-info/WHEEL
wsgigzip-0.1.4.dist-info/metadata.json
wsgigzip-0.1.4.dist-info/top_level.txt
