Metadata-Version: 2.0
Name: wsgigzip
Version: 0.1.4
Summary: Decorator for flup's gzip compression WSGI middleware.
Home-page: https://bitbucket.org/lcrees/wsgigzip/
Author: Lynn C. Rees
Author-email: lcrees@gmail.com
License: BSD
Keywords: WSGI middleware compression gzip flup decorator
Platform: UNKNOWN
Classifier: Development Status :: 4 - Beta
Classifier: Environment :: Web Environment
Classifier: License :: OSI Approved :: BSD License
Classifier: Operating System :: OS Independent
Classifier: Programming Language :: Python
Classifier: Programming Language :: Python :: 2
Classifier: Programming Language :: Python :: 3
Classifier: Topic :: Internet :: WWW/HTTP :: WSGI :: Middleware
Requires: setuptools
